{
  "positions": [
    {
      "coin": "ETH",
      "side": "LONG",
      "size": 3189.8949,
      "entry_price": 1997.53,
      "position_value_usd": 5736069.00918,
      "leverage": 8,
      "unrealized_pnl": -635869.38455,
      "liquidation_price": 20.9039424535
    },
    {
      "coin": "AAVE",
      "side": "LONG",
      "size": 40102.43,
      "entry_price": 81.9526,
      "position_value_usd": 3895790.66478,
      "leverage": 10,
      "unrealized_pnl": 609289.10476,
      "liquidation_price": 0.0
    },
    {
      "coin": "NEAR",
      "side": "LONG",
      "size": 266223.0,
      "entry_price": 1.8793,
      "position_value_usd": 503480.9376,
      "leverage": 10,
      "unrealized_pnl": 3167.45214,
      "liquidation_price": 0.0
    },
    {
      "coin": "XPL",
      "side": "LONG",
      "size": 12188868.0,
      "entry_price": 0.085907,
      "position_value_usd": 1110344.93046,
      "leverage": 5,
      "unrealized_pnl": 63225.414342,
      "liquidation_price": 0.0
    }
  ],
  "timestamp_ms": 1783767027285
}