{
  "positions": [
    {
      "coin": "BTC",
      "side": "LONG",
      "size": 1000.0,
      "entry_price": 62353.6,
      "position_value_usd": 66241000.0,
      "leverage": 40,
      "unrealized_pnl": 3887345.11882,
      "liquidation_price": 59428.8700815291
    },
    {
      "coin": "ETH",
      "side": "LONG",
      "size": 10000.0,
      "entry_price": 1761.94,
      "position_value_usd": 19312000.0,
      "leverage": 20,
      "unrealized_pnl": 1692518.96602,
      "liquidation_price": 1244.7736434194
    }
  ],
  "timestamp_ms": 1784691710368
}