{
  "positions": [
    {
      "coin": "BCH",
      "side": "SHORT",
      "size": 20.0,
      "entry_price": 630.0,
      "position_value_usd": 4052.2,
      "leverage": 10,
      "unrealized_pnl": 8547.8,
      "liquidation_price": 109943.229733619
    },
    {
      "coin": "WLD",
      "side": "SHORT",
      "size": 1160000.0,
      "entry_price": 0.55661,
      "position_value_usd": 500319.6,
      "leverage": 10,
      "unrealized_pnl": 145358.978893,
      "liquidation_price": 2.3233896506
    },
    {
      "coin": "UNI",
      "side": "SHORT",
      "size": 1000.0,
      "entry_price": 8.2836,
      "position_value_usd": 2981.3,
      "leverage": 10,
      "unrealized_pnl": 5302.3,
      "liquidation_price": 2197.7936946724
    },
    {
      "coin": "ZRO",
      "side": "SHORT",
      "size": 3500.0,
      "entry_price": 2.40911,
      "position_value_usd": 2869.055,
      "leverage": 5,
      "unrealized_pnl": 5562.836129,
      "liquidation_price": 599.404928547
    },
    {
      "coin": "NEAR",
      "side": "SHORT",
      "size": 24999.9,
      "entry_price": 2.45554,
      "position_value_usd": 47457.31017,
      "leverage": 10,
      "unrealized_pnl": 13930.953322,
      "liquidation_price": 89.6911469583
    },
    {
      "coin": "ORDI",
      "side": "SHORT",
      "size": 1100.0,
      "entry_price": 7.6907,
      "position_value_usd": 4261.95,
      "leverage": 3,
      "unrealized_pnl": 4197.890557,
      "liquidation_price": 1799.630095641
    },
    {
      "coin": "ZEN",
      "side": "SHORT",
      "size": 1000.0,
      "entry_price": 24.3079,
      "position_value_usd": 4143.0,
      "leverage": 5,
      "unrealized_pnl": 20164.976211,
      "liquidation_price": 2099.1911949145
    },
    {
      "coin": "FIL",
      "side": "SHORT",
      "size": 7000.0,
      "entry_price": 3.24032,
      "position_value_usd": 5158.79,
      "leverage": 5,
      "unrealized_pnl": 17523.467507,
      "liquidation_price": 300.0295692735
    },
    {
      "coin": "kLUNC",
      "side": "SHORT",
      "size": 29000.0,
      "entry_price": 0.043744,
      "position_value_usd": 1785.588,
      "leverage": 3,
      "unrealized_pnl": -517.003254,
      "liquidation_price": 68.1764394209
    },
    {
      "coin": "STRK",
      "side": "SHORT",
      "size": 170000.0,
      "entry_price": 0.23365,
      "position_value_usd": 5190.1,
      "leverage": 5,
      "unrealized_pnl": 34530.721073,
      "liquidation_price": 12.3543429113
    },
    {
      "coin": "TNSR",
      "side": "SHORT",
      "size": 90777.7,
      "entry_price": 0.15671,
      "position_value_usd": 3174.496169,
      "leverage": 3,
      "unrealized_pnl": 11051.465827,
      "liquidation_price": 21.795062569
    },
    {
      "coin": "XLM",
      "side": "SHORT",
      "size": 25000.0,
      "entry_price": 0.22999,
      "position_value_usd": 4442.5,
      "leverage": 5,
      "unrealized_pnl": 1307.25,
      "liquidation_price": 83.9796277966
    },
    {
      "coin": "VIRTUAL",
      "side": "SHORT",
      "size": 3000.0,
      "entry_price": 1.443,
      "position_value_usd": 1647.24,
      "leverage": 5,
      "unrealized_pnl": 2681.76,
      "liquidation_price": 698.8984783048
    },
    {
      "coin": "TRUMP",
      "side": "SHORT",
      "size": 2000.0,
      "entry_price": 8.3305,
      "position_value_usd": 3355.2,
      "leverage": 10,
      "unrealized_pnl": 13305.812579,
      "liquidation_price": 1099.0837973362
    },
    {
      "coin": "MELANIA",
      "side": "SHORT",
      "size": 100000.0,
      "entry_price": 0.19318,
      "position_value_usd": 7544.0,
      "leverage": 3,
      "unrealized_pnl": 11774.846145,
      "liquidation_price": 19.828751552
    },
    {
      "coin": "ANIME",
      "side": "SHORT",
      "size": 502714.0,
      "entry_price": 0.009141,
      "position_value_usd": 1427.70776,
      "leverage": 3,
      "unrealized_pnl": 3167.700747,
      "liquidation_price": 3.9321738861
    },
    {
      "coin": "VVV",
      "side": "SHORT",
      "size": 499.0,
      "entry_price": 9.8186,
      "position_value_usd": 6865.741,
      "leverage": 3,
      "unrealized_pnl": -1966.25725,
      "liquidation_price": 3972.3384693478
    },
    {
      "coin": "BERA",
      "side": "SHORT",
      "size": 17000.0,
      "entry_price": 0.96741,
      "position_value_usd": 3632.9,
      "leverage": 5,
      "unrealized_pnl": 12813.183966,
      "liquidation_price": 123.4518291126
    },
    {
      "coin": "AVNT",
      "side": "SHORT",
      "size": 20000.0,
      "entry_price": 0.41,
      "position_value_usd": 1882.08,
      "leverage": 5,
      "unrealized_pnl": 6317.92,
      "liquidation_price": 104.8465137457
    },
    {
      "coin": "STBL",
      "side": "SHORT",
      "size": 160000.0,
      "entry_price": 0.091833,
      "position_value_usd": 4178.4,
      "leverage": 3,
      "unrealized_pnl": 10515.0,
      "liquidation_price": 12.37193472
    },
    {
      "coin": "0G",
      "side": "SHORT",
      "size": 10000.0,
      "entry_price": 1.141549,
      "position_value_usd": 2161.9,
      "leverage": 3,
      "unrealized_pnl": 9253.599992,
      "liquidation_price": 197.7493055205
    },
    {
      "coin": "ZEC",
      "side": "SHORT",
      "size": 1.0,
      "entry_price": 571.1459,
      "position_value_usd": 407.52,
      "leverage": 10,
      "unrealized_pnl": 163.625944,
      "liquidation_price": 2195219.914672381
    },
    {
      "coin": "MET",
      "side": "SHORT",
      "size": 50000.0,
      "entry_price": 0.453132,
      "position_value_usd": 8571.0,
      "leverage": 3,
      "unrealized_pnl": 14085.6,
      "liquidation_price": 39.6780431041
    },
    {
      "coin": "ICP",
      "side": "SHORT",
      "size": 1000.0,
      "entry_price": 7.07,
      "position_value_usd": 2189.9,
      "leverage": 5,
      "unrealized_pnl": 4880.1,
      "liquidation_price": 2097.2380949145
    },
    {
      "coin": "FOGO",
      "side": "SHORT",
      "size": 200000.0,
      "entry_price": 0.038816,
      "position_value_usd": 1802.2,
      "leverage": 3,
      "unrealized_pnl": 5961.1,
      "liquidation_price": 9.885666776
    },
    {
      "coin": "LIT",
      "side": "SHORT",
      "size": 2000.0,
      "entry_price": 2.667108,
      "position_value_usd": 3635.0,
      "leverage": 3,
      "unrealized_pnl": 1699.216829,
      "liquidation_price": 1.9412816105
    },
    {
      "coin": "DASH",
      "side": "SHORT",
      "size": 170.0,
      "entry_price": 43.3121,
      "position_value_usd": 5646.55,
      "leverage": 5,
      "unrealized_pnl": 1716.513812,
      "liquidation_price": 12357.027911262
    },
    {
      "coin": "CHIP",
      "side": "SHORT",
      "size": 70000.0,
      "entry_price": 0.120063,
      "position_value_usd": 2195.34,
      "leverage": 3,
      "unrealized_pnl": 6209.082723,
      "liquidation_price": 28.2503785029
    }
  ],
  "timestamp_ms": 1782764542721
}