{
  "positions": [
    {
      "coin": "LINK",
      "side": "SHORT",
      "size": 200000.0,
      "entry_price": 7.55579,
      "position_value_usd": 1725240.0,
      "leverage": 10,
      "unrealized_pnl": -214081.582923,
      "liquidation_price": 36.3297469039
    },
    {
      "coin": "HYPE",
      "side": "SHORT",
      "size": 70000.0,
      "entry_price": 62.8016,
      "position_value_usd": 4145400.0,
      "leverage": 10,
      "unrealized_pnl": 250714.50347,
      "liquidation_price": 138.372991154
    },
    {
      "coin": "VVV",
      "side": "SHORT",
      "size": 80000.0,
      "entry_price": 20.519,
      "position_value_usd": 969360.0,
      "leverage": 3,
      "unrealized_pnl": 672160.43411,
      "liquidation_price": 74.4499805338
    },
    {
      "coin": "PAXG",
      "side": "SHORT",
      "size": 0.454,
      "entry_price": 4596.297,
      "position_value_usd": 1872.523,
      "leverage": 10,
      "unrealized_pnl": 214.195909,
      "liquidation_price": 11953766.517755305
    }
  ],
  "timestamp_ms": 1784750813382
}