{
  "positions": [
    {
      "coin": "OP",
      "side": "SHORT",
      "size": 3990559.6,
      "entry_price": 0.23182,
      "position_value_usd": 411745.939528,
      "leverage": 5,
      "unrealized_pnl": 513370.333355,
      "liquidation_price": 1.0859561959
    },
    {
      "coin": "SUI",
      "side": "SHORT",
      "size": 267780.6,
      "entry_price": 0.74665,
      "position_value_usd": 190284.89436,
      "leverage": 10,
      "unrealized_pnl": 9653.88379,
      "liquidation_price": 16.0536855303
    },
    {
      "coin": "kPEPE",
      "side": "SHORT",
      "size": 98328416.0,
      "entry_price": 0.003044,
      "position_value_usd": 240314.648704,
      "leverage": 10,
      "unrealized_pnl": 59019.936608,
      "liquidation_price": 0.0442282656
    },
    {
      "coin": "APT",
      "side": "SHORT",
      "size": 710371.46,
      "entry_price": 1.1221,
      "position_value_usd": 428567.101818,
      "leverage": 10,
      "unrealized_pnl": 368574.599399,
      "liquidation_price": 6.3870073707
    },
    {
      "coin": "DOT",
      "side": "SHORT",
      "size": 607110.6,
      "entry_price": 1.32886,
      "position_value_usd": 512328.493128,
      "leverage": 10,
      "unrealized_pnl": 294437.531568,
      "liquidation_price": 7.4899556259
    },
    {
      "coin": "ADA",
      "side": "SHORT",
      "size": 6580923.0,
      "entry_price": 0.235449,
      "position_value_usd": 976608.9732,
      "leverage": 10,
      "unrealized_pnl": 572866.28373,
      "liquidation_price": 0.7727167788
    },
    {
      "coin": "NEAR",
      "side": "LONG",
      "size": 492341.5,
      "entry_price": 1.82836,
      "position_value_usd": 942637.0359,
      "leverage": 10,
      "unrealized_pnl": 42458.19504,
      "liquidation_price": 0.0
    },
    {
      "coin": "STRK",
      "side": "SHORT",
      "size": 10595485.2,
      "entry_price": 0.04206,
      "position_value_usd": 311083.445472,
      "leverage": 5,
      "unrealized_pnl": 134595.372118,
      "liquidation_price": 0.3995013299
    },
    {
      "coin": "EIGEN",
      "side": "SHORT",
      "size": 3121652.67,
      "entry_price": 0.3322,
      "position_value_usd": 738270.856455,
      "leverage": 5,
      "unrealized_pnl": 298941.097251,
      "liquidation_price": 1.4928303474
    },
    {
      "coin": "HYPE",
      "side": "SHORT",
      "size": 15411.76,
      "entry_price": 71.3729,
      "position_value_usd": 989650.75664,
      "leverage": 10,
      "unrealized_pnl": 110331.72201,
      "liquidation_price": 330.8013754292
    },
    {
      "coin": "TRUMP",
      "side": "SHORT",
      "size": 563346.0,
      "entry_price": 2.83697,
      "position_value_usd": 959378.238,
      "leverage": 8,
      "unrealized_pnl": 638822.776563,
      "liquidation_price": 8.9961744419
    },
    {
      "coin": "WLFI",
      "side": "SHORT",
      "size": 21126000.0,
      "entry_price": 0.082036,
      "position_value_usd": 1245905.85,
      "leverage": 5,
      "unrealized_pnl": 487192.862037,
      "liquidation_price": 0.2446148269
    },
    {
      "coin": "LIT",
      "side": "LONG",
      "size": 619365.0,
      "entry_price": 1.456383,
      "position_value_usd": 1131455.982,
      "leverage": 5,
      "unrealized_pnl": 229422.8212,
      "liquidation_price": 0.0
    }
  ],
  "timestamp_ms": 1782578973613
}