{
  "positions": [
    {
      "coin": "OP",
      "side": "SHORT",
      "size": 3990559.6,
      "entry_price": 0.23182,
      "position_value_usd": 403924.442712,
      "leverage": 5,
      "unrealized_pnl": 521191.830171,
      "liquidation_price": 0.8903204397
    },
    {
      "coin": "SUI",
      "side": "SHORT",
      "size": 267780.6,
      "entry_price": 0.74665,
      "position_value_usd": 189208.416348,
      "leverage": 10,
      "unrealized_pnl": 10730.361802,
      "liquidation_price": 13.0260028648
    },
    {
      "coin": "kPEPE",
      "side": "SHORT",
      "size": 98328416.0,
      "entry_price": 0.003044,
      "position_value_usd": 278466.074112,
      "leverage": 10,
      "unrealized_pnl": 20868.5112,
      "liquidation_price": 0.0363818382
    },
    {
      "coin": "APT",
      "side": "SHORT",
      "size": 710371.46,
      "entry_price": 1.1221,
      "position_value_usd": 473107.39236,
      "leverage": 10,
      "unrealized_pnl": 324034.308857,
      "liquidation_price": 5.3099118576
    },
    {
      "coin": "DOT",
      "side": "SHORT",
      "size": 607110.6,
      "entry_price": 1.32886,
      "position_value_usd": 580913.77761,
      "leverage": 10,
      "unrealized_pnl": 225852.247086,
      "liquidation_price": 6.3247529815
    },
    {
      "coin": "ADA",
      "side": "SHORT",
      "size": 6580923.0,
      "entry_price": 0.235449,
      "position_value_usd": 1052750.25231,
      "leverage": 10,
      "unrealized_pnl": 496725.00462,
      "liquidation_price": 0.6612526387
    },
    {
      "coin": "NEAR",
      "side": "LONG",
      "size": 492341.5,
      "entry_price": 1.82836,
      "position_value_usd": 1064048.4498,
      "leverage": 10,
      "unrealized_pnl": 163869.60894,
      "liquidation_price": 0.0
    },
    {
      "coin": "STRK",
      "side": "SHORT",
      "size": 10595485.2,
      "entry_price": 0.04206,
      "position_value_usd": 362047.729284,
      "leverage": 5,
      "unrealized_pnl": 83631.088306,
      "liquidation_price": 0.3313675587
    },
    {
      "coin": "EIGEN",
      "side": "SHORT",
      "size": 3121652.67,
      "entry_price": 0.3322,
      "position_value_usd": 951479.733816,
      "leverage": 5,
      "unrealized_pnl": 85732.21989,
      "liquidation_price": 1.3135452603
    },
    {
      "coin": "HYPE",
      "side": "SHORT",
      "size": 15411.76,
      "entry_price": 71.3729,
      "position_value_usd": 1022647.3348,
      "leverage": 10,
      "unrealized_pnl": 77335.14385,
      "liquidation_price": 280.4059874524
    },
    {
      "coin": "TRUMP",
      "side": "SHORT",
      "size": 563346.0,
      "entry_price": 2.83697,
      "position_value_usd": 1074413.4912,
      "leverage": 8,
      "unrealized_pnl": 523787.523363,
      "liquidation_price": 7.7631081743
    },
    {
      "coin": "WLFI",
      "side": "SHORT",
      "size": 21126000.0,
      "entry_price": 0.082036,
      "position_value_usd": 1254461.88,
      "leverage": 5,
      "unrealized_pnl": 478636.832037,
      "liquidation_price": 0.2084357765
    },
    {
      "coin": "LIT",
      "side": "LONG",
      "size": 619365.0,
      "entry_price": 1.456383,
      "position_value_usd": 1012847.5845,
      "leverage": 5,
      "unrealized_pnl": 110814.4237,
      "liquidation_price": 0.0
    }
  ],
  "timestamp_ms": 1782106651730
}