{
  "positions": [
    {
      "coin": "LDO",
      "side": "LONG",
      "size": 1759490.8,
      "entry_price": 0.99916,
      "position_value_usd": 455039.510696,
      "leverage": 1,
      "unrealized_pnl": -1302983.25213,
      "liquidation_price": 0.0
    },
    {
      "coin": "TON",
      "side": "LONG",
      "size": 1447915.9,
      "entry_price": 3.44284,
      "position_value_usd": 2415123.7212,
      "leverage": 1,
      "unrealized_pnl": -2569830.299997,
      "liquidation_price": 0.0
    },
    {
      "coin": "ONDO",
      "side": "LONG",
      "size": 1745500.0,
      "entry_price": 0.992029,
      "position_value_usd": 616946.975,
      "leverage": 1,
      "unrealized_pnl": -1114641.265749,
      "liquidation_price": 0.0
    },
    {
      "coin": "ENA",
      "side": "LONG",
      "size": 5431981.0,
      "entry_price": 0.57887,
      "position_value_usd": 421434.813904,
      "leverage": 1,
      "unrealized_pnl": -2722978.367596,
      "liquidation_price": 0.0
    },
    {
      "coin": "WLFI",
      "side": "LONG",
      "size": 5929745.0,
      "entry_price": 0.195226,
      "position_value_usd": 351402.618445,
      "leverage": 1,
      "unrealized_pnl": -806243.494315,
      "liquidation_price": 0.0
    },
    {
      "coin": "STBL",
      "side": "LONG",
      "size": 1915072.0,
      "entry_price": 0.165307,
      "position_value_usd": 45670.637056,
      "leverage": 1,
      "unrealized_pnl": -270904.532734,
      "liquidation_price": 0.0
    }
  ],
  "timestamp_ms": 1781331761154
}