{
  "positions": [
    {
      "coin": "BTC",
      "side": "LONG",
      "size": 31.31624,
      "entry_price": 65531.2,
      "position_value_usd": 2020805.65096,
      "leverage": 20,
      "unrealized_pnl": -31385.377026,
      "liquidation_price": 0.0
    },
    {
      "coin": "ETH",
      "side": "LONG",
      "size": 8092.4521,
      "entry_price": 1658.44,
      "position_value_usd": 15167682.97103,
      "leverage": 15,
      "unrealized_pnl": 1746818.442647,
      "liquidation_price": 1406.7155137522
    }
  ],
  "timestamp_ms": 1784470398160
}