{
  "positions": [
    {
      "coin": "BTC",
      "side": "LONG",
      "size": 31.31624,
      "entry_price": 65531.2,
      "position_value_usd": 2036714.30088,
      "leverage": 20,
      "unrealized_pnl": -15476.727106,
      "liquidation_price": 0.0
    },
    {
      "coin": "ETH",
      "side": "LONG",
      "size": 8092.4521,
      "entry_price": 1658.44,
      "position_value_usd": 15365948.04748,
      "leverage": 15,
      "unrealized_pnl": 1945083.519097,
      "liquidation_price": 1407.1766760592
    }
  ],
  "timestamp_ms": 1784812290135
}