{
  "positions": [
    {
      "coin": "BTC",
      "side": "LONG",
      "size": 70.0,
      "entry_price": 59912.8,
      "position_value_usd": 4434150.0,
      "leverage": 10,
      "unrealized_pnl": 240250.0,
      "liquidation_price": 43353.6626278192
    },
    {
      "coin": "HYPE",
      "side": "LONG",
      "size": 15000.25,
      "entry_price": 63.4446,
      "position_value_usd": 1012951.88225,
      "leverage": 5,
      "unrealized_pnl": 61266.104561,
      "liquidation_price": 0.0
    }
  ],
  "timestamp_ms": 1783621928833
}