{
  "positions": [
    {
      "coin": "BTC",
      "side": "LONG",
      "size": 70.0,
      "entry_price": 59912.8,
      "position_value_usd": 4415110.0,
      "leverage": 10,
      "unrealized_pnl": 221210.0,
      "liquidation_price": 43428.5257020181
    },
    {
      "coin": "HYPE",
      "side": "LONG",
      "size": 15000.25,
      "entry_price": 63.4446,
      "position_value_usd": 1007941.79875,
      "leverage": 5,
      "unrealized_pnl": 56256.021061,
      "liquidation_price": 0.0
    }
  ],
  "timestamp_ms": 1783646042746
}