{
  "positions": [
    {
      "coin": "ETH",
      "side": "SHORT",
      "size": 123.0,
      "entry_price": 1572.6,
      "position_value_usd": 226738.2,
      "leverage": 25,
      "unrealized_pnl": -33308.33939,
      "liquidation_price": 11412.338266029
    },
    {
      "coin": "SOL",
      "side": "SHORT",
      "size": 2880.0,
      "entry_price": 80.1037,
      "position_value_usd": 215919.36,
      "leverage": 20,
      "unrealized_pnl": 14779.41915,
      "liquidation_price": 481.6518763062
    },
    {
      "coin": "AAVE",
      "side": "SHORT",
      "size": 550.0,
      "entry_price": 85.9128,
      "position_value_usd": 48879.6,
      "leverage": 10,
      "unrealized_pnl": -1627.54021,
      "liquidation_price": 2167.6927703134
    },
    {
      "coin": "ZRO",
      "side": "SHORT",
      "size": 138000.0,
      "entry_price": 0.89951,
      "position_value_usd": 108267.9,
      "leverage": 5,
      "unrealized_pnl": 15865.841621,
      "liquidation_price": 8.6931072784
    },
    {
      "coin": "NEAR",
      "side": "SHORT",
      "size": 100000.0,
      "entry_price": 1.79094,
      "position_value_usd": 191473.0,
      "leverage": 10,
      "unrealized_pnl": -12378.91028,
      "liquidation_price": 13.3482442367
    },
    {
      "coin": "JTO",
      "side": "SHORT",
      "size": 318000.0,
      "entry_price": 0.727658,
      "position_value_usd": 172133.4,
      "leverage": 5,
      "unrealized_pnl": 59262.15783,
      "liquidation_price": 3.9733154227
    },
    {
      "coin": "ENA",
      "side": "SHORT",
      "size": 1380000.0,
      "entry_price": 0.071424,
      "position_value_usd": 109846.62,
      "leverage": 5,
      "unrealized_pnl": -11281.213464,
      "liquidation_price": 0.9081145244
    },
    {
      "coin": "MNT",
      "side": "SHORT",
      "size": 330000.0,
      "entry_price": 0.40377,
      "position_value_usd": 137474.7,
      "leverage": 5,
      "unrealized_pnl": -4228.949763,
      "liquidation_price": 3.7238048619
    },
    {
      "coin": "HYPE",
      "side": "SHORT",
      "size": 21800.0,
      "entry_price": 65.3282,
      "position_value_usd": 1290974.2,
      "leverage": 10,
      "unrealized_pnl": 133181.99294,
      "liquidation_price": 111.6663130125
    },
    {
      "coin": "XPL",
      "side": "SHORT",
      "size": 2000000.0,
      "entry_price": 0.091448,
      "position_value_usd": 163166.0,
      "leverage": 10,
      "unrealized_pnl": 19731.239735,
      "liquidation_price": 0.6532587118
    },
    {
      "coin": "XMR",
      "side": "SHORT",
      "size": 388.0,
      "entry_price": 314.281,
      "position_value_usd": 129809.28,
      "leverage": 5,
      "unrealized_pnl": -7868.25134,
      "liquidation_price": 3147.3973825117
    },
    {
      "coin": "GRAM",
      "side": "SHORT",
      "size": 168000.0,
      "entry_price": 1.667168,
      "position_value_usd": 246388.8,
      "leverage": 5,
      "unrealized_pnl": 33695.5195,
      "liquidation_price": 7.9629149072
    }
  ],
  "timestamp_ms": 1784392187863
}