{
  "positions": [
    {
      "coin": "ETH",
      "side": "LONG",
      "size": 7003.8263,
      "entry_price": 1812.69,
      "position_value_usd": 12575370.12165,
      "leverage": 5,
      "unrealized_pnl": -120410.962226,
      "liquidation_price": 949.8811247445
    },
    {
      "coin": "SOL",
      "side": "LONG",
      "size": 20022.69,
      "entry_price": 66.0904,
      "position_value_usd": 1560448.32246,
      "leverage": 20,
      "unrealized_pnl": 237139.72343,
      "liquidation_price": 0.0
    },
    {
      "coin": "LTC",
      "side": "LONG",
      "size": 15516.16,
      "entry_price": 44.2456,
      "position_value_usd": 692656.89856,
      "leverage": 10,
      "unrealized_pnl": 6134.56368,
      "liquidation_price": 0.0
    },
    {
      "coin": "SUI",
      "side": "LONG",
      "size": 1916331.0,
      "entry_price": 0.72482,
      "position_value_usd": 1415229.60681,
      "leverage": 10,
      "unrealized_pnl": 26225.131447,
      "liquidation_price": 0.0
    },
    {
      "coin": "PURR",
      "side": "LONG",
      "size": 12815799.0,
      "entry_price": 0.123644,
      "position_value_usd": 1170697.607052,
      "leverage": 3,
      "unrealized_pnl": -413909.788444,
      "liquidation_price": 0.0
    },
    {
      "coin": "HYPE",
      "side": "LONG",
      "size": 100028.87,
      "entry_price": 68.0554,
      "position_value_usd": 6746247.07941,
      "leverage": 10,
      "unrealized_pnl": -61258.178773,
      "liquidation_price": 6.3646715879
    },
    {
      "coin": "VVV",
      "side": "LONG",
      "size": 101371.1,
      "entry_price": 16.7791,
      "position_value_usd": 1130186.3939,
      "leverage": 3,
      "unrealized_pnl": -570734.37663,
      "liquidation_price": 0.0
    },
    {
      "coin": "ZEC",
      "side": "LONG",
      "size": 13901.78,
      "entry_price": 340.9101,
      "position_value_usd": 7028461.9324,
      "leverage": 5,
      "unrealized_pnl": 2289204.0588,
      "liquidation_price": 66.0969861304
    }
  ],
  "timestamp_ms": 1783712693026
}